exper/__init__.py
exper/comms.py
exper/core.py
exper/cuda_utils.py
exper/engine.py
exper/loss_utils.py
exper/pretty.py
exper/tasks.py
exper-0.2.0.dist-info/METADATA
exper-0.2.0.dist-info/WHEEL
exper-0.2.0.dist-info/top_level.txt
exper-0.2.0.dist-info/RECORD
