Metadata-Version: 2.1
Name: exper
Version: 0.2.0
Summary: This is a python package for running deep learning experiments. Users can rapidly run their experiments by importing this module.
Author: Mrzz
Requires-Dist: torch
Requires-Dist: torch-geometric
